{
  "name": "hexcasting.entry.pigments",
  "category": "hexcasting:items",
  "icon": "hexcasting:uuid_colorizer",
  "sortnum": 5,
  "advancement": "hexcasting:root",
  "read_by_default": true,
  "pages": [
    {
      "type": "patchouli:text",
      "text": "hexcasting.page.pigments1"
    },
    {
      "type": "patchouli:text",
      "text": "hexcasting.page.pigments2"
    },
    {
      "type": "hexcasting:crafting_multi",
      "heading": "hexcasting.page.pigments3header",
      "text": "hexcasting.page.pigments3",
      "recipes": [
        "hexcasting:dye_colorizer_white",
        "hexcasting:dye_colorizer_orange",
        "hexcasting:dye_colorizer_magenta",
        "hexcasting:dye_colorizer_light_blue",
        "hexcasting:dye_colorizer_yellow",
        "hexcasting:dye_colorizer_lime",
        "hexcasting:dye_colorizer_pink",
        "hexcasting:dye_colorizer_gray",
        "hexcasting:dye_colorizer_light_gray",
        "hexcasting:dye_colorizer_cyan",
        "hexcasting:dye_colorizer_purple",
        "hexcasting:dye_colorizer_blue",
        "hexcasting:dye_colorizer_brown",
        "hexcasting:dye_colorizer_green",
        "hexcasting:dye_colorizer_red"
      ]
    },
    {
      "type": "patchouli:crafting",
      "recipe": "hexcasting:pride_colorizer_0",
      "recipe2": "hexcasting:pride_colorizer_1"
    },
    {
      "type": "patchouli:crafting",
      "recipe": "hexcasting:pride_colorizer_2",
      "recipe2": "hexcasting:pride_colorizer_3"
    },
    {
      "type": "patchouli:crafting",
      "recipe": "hexcasting:pride_colorizer_4",
      "recipe2": "hexcasting:pride_colorizer_5"
    },
    {
      "type": "patchouli:crafting",
      "recipe": "hexcasting:pride_colorizer_6",
      "recipe2": "hexcasting:pride_colorizer_7"
    },
    {
      "type": "patchouli:crafting",
      "recipe": "hexcasting:pride_colorizer_8",
      "recipe2": "hexcasting:pride_colorizer_9"
    },
    {
      "type": "patchouli:crafting",
      "recipe": "hexcasting:pride_colorizer_10",
      "recipe2": "hexcasting:pride_colorizer_11"
    },
    {
      "type": "patchouli:crafting",
      "recipe": "hexcasting:pride_colorizer_12",
      "recipe2": "hexcasting:pride_colorizer_13"
    },
    {
      "type": "patchouli:crafting",
      "recipe": "hexcasting:uuid_colorizer",
      "text": "hexcasting.page.pigments4"
    }
  ]
}
